flask_opencv_streamer/__init__.py
flask_opencv_streamer/login_manager.py
flask_opencv_streamer/streamer.py
flask_opencv_streamer-1.4.dist-info/LICENSE
flask_opencv_streamer-1.4.dist-info/METADATA
flask_opencv_streamer-1.4.dist-info/WHEEL
flask_opencv_streamer-1.4.dist-info/top_level.txt
flask_opencv_streamer-1.4.dist-info/RECORD
