Metadata-Version: 2.1
Name: flask-opencv-streamer
Version: 1.4
Summary: A Python package for easily streaming OpenCV footage, even with authentication
Home-page: https://github.com/oitsjustjose/Flask-OpenCV-Streamer
Author: Jose Stovall
Author-email: stovallj1995@gmail.com
License: GNU General Public License 3
Platform: UNKNOWN
